hstp/__init__.py
hstp/v1/__init__.py
hstp/v1/hstp_pb2.py
hstp/v1/hstp_pb2.pyi
hstp/v1/hstp_pb2_grpc.py
proto_kortex-2.6.0.dist-info/LICENSE.txt
proto_kortex-2.6.0.dist-info/METADATA
proto_kortex-2.6.0.dist-info/WHEEL
proto_kortex-2.6.0.dist-info/RECORD
