Metadata-Version: 2.1
Name: proto-kortex
Version: 2.6.0
Summary: 
Author: VERSES AI
Author-email: engineering@verses.ai
Requires-Python: >=3.10,<4.0
Classifier: Programming Language :: Python :: 3
Classifier: Programming Language :: Python :: 3.10
Classifier: Programming Language :: Python :: 3.11
Classifier: Programming Language :: Python :: 3.12
Requires-Dist: grpcio (>=1.54.2,<2.0.0)
Requires-Dist: grpcio-tools (>=1.54.2,<2.0.0)
